{
   "abstract" : "Encodes integers into a short and easy to read and pronounce \"locator string\"",
   "author" : [
      "Jesse Vincent <jesse@bestpractical.com>"
   ],
   "dynamic_config" : 0,
   "generated_by" : "Module::Install version 0.64, CPAN::Meta::Converter version 2.133380",
   "license" : [
      "perl_5"
   ],
   "meta-spec" : {
      "url" : "http://search.cpan.org/perldoc?CPAN::Meta::Spec",
      "version" : "2"
   },
   "name" : "Number-RecordLocator",
   "no_index" : {
      "directory" : [
         "inc",
         "t"
      ]
   },
   "prereqs" : {
      "build" : {
         "requires" : {
            "ExtUtils::MakeMaker" : "0"
         }
      },
      "runtime" : {
         "requires" : {
            "ExtUtils::MakeMaker" : "6.6302",
            "Test::More" : "0"
         }
      }
   },
   "release_status" : "stable",
   "version" : "0.003"
}
